mcp_day_server/__init__.py
mcp_day_server/__main__.py
mcp_day_server/server.py
mcp_day_server-1.2.0.dist-info/METADATA
mcp_day_server-1.2.0.dist-info/WHEEL
mcp_day_server-1.2.0.dist-info/entry_points.txt
mcp_day_server-1.2.0.dist-info/RECORD
