Metadata-Version: 2.4
Name: mcp-day-server
Version: 1.2.0
Requires-Python: >=3.12
Requires-Dist: mcp>=1.8.0
